process_nitta/__init__.py
process_nitta/agis.py
process_nitta/csv_config.py
process_nitta/dma.py
process_nitta/instron.py
process_nitta/ir_nicolet.py
process_nitta/models.py
process_nitta/raman.py
process_nitta-0.1.13.dist-info/METADATA
process_nitta-0.1.13.dist-info/WHEEL
process_nitta-0.1.13.dist-info/licenses/LICENSE
process_nitta-0.1.13.dist-info/RECORD
